<?xml version="1.0" encoding="UTF-8"?>
<java version="1.8.0_241" class="java.beans.XMLDecoder">
 <object class="java.util.ArrayList">
  <void method="add">
   <object class="Sportsman">
    <void property="email">
     <string>t</string>
    </void>
    <void property="firstName">
     <string>o</string>
    </void>
    <void property="lastName">
     <string>o</string>
    </void>
    <void property="password">
     <string>5b35dd9b6c0f45c8479961acb2dc9ab5c8295685275d55ff2adc76370cd1630bc0a060d583e614805941d8afd5b4dd7f34e9e343fcd65ed4e3b9089580363a8b</string>
    </void>
    <void property="salt">
     <array class="byte" length="16">
      <void index="0">
       <byte>-75</byte>
      </void>
      <void index="1">
       <byte>97</byte>
      </void>
      <void index="2">
       <byte>6</byte>
      </void>
      <void index="3">
       <byte>82</byte>
      </void>
      <void index="4">
       <byte>-49</byte>
      </void>
      <void index="5">
       <byte>7</byte>
      </void>
      <void index="7">
       <byte>22</byte>
      </void>
      <void index="8">
       <byte>-24</byte>
      </void>
      <void index="9">
       <byte>27</byte>
      </void>
      <void index="10">
       <byte>28</byte>
      </void>
      <void index="11">
       <byte>-76</byte>
      </void>
      <void index="12">
       <byte>60</byte>
      </void>
      <void index="13">
       <byte>-16</byte>
      </void>
      <void index="14">
       <byte>121</byte>
      </void>
      <void index="15">
       <byte>35</byte>
      </void>
     </array>
    </void>
   </object>
  </void>
 </object>
</java>
